[
  {
    "id": 430,
    "title": "Masters of American Photography",
    "description": "Friday, September 21, 2001 - Wednesday, January 02, 2002",
    "objectIds": [
      10712,
      1770,
      1718,
      19662,
      1847,
      1922,
      19821,
      1902,
      1973,
      2044,
      10670,
      2320,
      11286,
      2977,
      3448,
      3516,
      3754,
      3757,
      3845,
      4831,
      10749,
      10809,
      11330,
      11914,
      43378
    ],
    "type": "exhibition"
  },
  {
    "id": 1667,
    "title": "Governor's Residence 2014-2016 (B)",
    "description": "Thursday, August 28, 2014 - Friday, August 28, 2015",
    "objectIds": [
      1970,
      11286,
      2844,
      3567,
      3571,
      3581,
      25351,
      25293,
      25294,
      25295,
      25305,
      25297,
      25289,
      4806,
      83081,
      108266,
      112663,
      114175,
      120108
    ],
    "type": "exhibition"
  }
]
