[
  {
    "id": 1928,
    "title": "A Selection of Japanese Art from the Mary and Jackson Burke Collection",
    "description": null,
    "objectIds": [
      6615,
      6632,
      99427,
      122070,
      122073,
      122099,
      122102,
      122103,
      122159,
      122160,
      122182,
      122353,
      122423,
      122483,
      122484,
      122489,
      122502,
      122963
    ],
    "type": "exhibition"
  },
  {
    "id": 1910,
    "title": "Masterpieces of Japanese Art from the Mary Griggs Burke Collection",
    "description": "Tuesday, March 28, 2000 - Sunday, June 25, 2000",
    "objectIds": [
      6614,
      6615,
      6645,
      99385,
      99386,
      99399,
      99427,
      121302,
      122069,
      122070,
      122073,
      122099,
      122105,
      122106,
      122109,
      122110,
      122115,
      122156,
      122159,
      122160,
      122166,
      122168,
      122204,
      122243,
      122244,
      122278,
      122352,
      122353,
      122374,
      122377,
      122389,
      122399,
      122403,
      122407,
      122423,
      122427,
      122434,
      122483,
      122484,
      122485,
      122502,
      122503,
      122505,
      122507,
      122544,
      123076,
      40036,
      122144,
      122145
    ],
    "type": "exhibition"
  },
  {
    "id": 1870,
    "title": "Die Kunst des Alten Japan: Meisterwerke aus der Mary and Jackson",
    "description": null,
    "objectIds": [
      122058,
      6919,
      99973,
      122066,
      122088,
      122099,
      6613,
      122109,
      122110,
      122144,
      122145,
      40037,
      123101,
      122182,
      122215,
      122216,
      122221,
      122242,
      122352,
      122353,
      122374,
      6654,
      122407,
      122423,
      122427,
      6624,
      122434,
      6622,
      122438,
      122484,
      122489,
      122491,
      122493,
      122504,
      122505,
      122507,
      122508,
      6632,
      122963,
      99421,
      6614,
      6615,
      37185,
      123100
    ],
    "type": "exhibition"
  }
]
