[
  {
    "title": "Krista Tippett on the intersection of art, science, and spirituality",
    "link": "http://new.artsmia.org/stories/krista-tippett-on-the-intersection-of-art-science-and-spirituality/",
    "objectIds": "1639",
    "type": "mia-story"
  },
  {
    "id": 12,
    "title": "Franz Marc and the Blue Rider",
    "description": "Sunday, April 08, 2001 - Sunday, July 15, 2001",
    "objectIds": [
      9920,
      1639,
      8842,
      32763,
      42135,
      42136,
      42265,
      7570,
      7871,
      9066,
      42266,
      42267,
      42268
    ],
    "type": "exhibition"
  },
  {
    "title": "A World Cup tribute: art from around the globe",
    "link": "http://new.artsmia.org/stories/a-world-cup-tribute-art-from-around-the-globe/",
    "objectIds": "111088 115752 115895 12155 12217 1387 15062 1517 1556 1639 1671 1785 1800 1822 2724 28662 28710 293 29496 31435 4684 4866 4867 516 5483 5485 57 59171 676 742 7487",
    "type": "mia-story"
  },
  {
    "id": 2161,
    "title": "Eugène Delacroix and Modernity",
    "description": "Wednesday, February 17, 2016 - Sunday, May 22, 2016",
    "objectIds": [
      601,
      799,
      1218,
      1414,
      1639,
      1978,
      4578,
      115814
    ],
    "type": "exhibition"
  },
  {
    "id": 1460,
    "title": "The Ecstasy of Color: Munch, Matisse and the Expressionists",
    "description": "Saturday, September 29, 2012 - Sunday, January 20, 2013",
    "objectIds": [
      1639,
      1224
    ],
    "type": "exhibition"
  },
  {
    "title": "Kandinsky, Study for Improvisation V",
    "link": "http://audio-tours.s3.amazonaws.com/p391.mp3",
    "type": "audio"
  }
]
