[
  {
    "id": 1130,
    "title": "Matisse e Michelangelo.  La seduzione della forma",
    "description": "Friday, February 11, 2011 - Sunday, June 12, 2011",
    "objectIds": [
      19531,
      1890
    ],
    "type": "exhibition"
  },
  {
    "id": 1649,
    "title": "More Matisse, Please: Paintings and Sculpture",
    "description": "Sunday, February 23, 2014 - Sunday, May 18, 2014",
    "objectIds": [
      766,
      1162,
      1411,
      1887,
      1888,
      1889,
      1890,
      6359,
      11463
    ],
    "type": "exhibition"
  },
  {
    "id": 733,
    "title": "Matisse: the Painter as Sculptor",
    "description": "Sunday, January 21, 2007 - Sunday, January 13, 2008",
    "objectIds": [
      1890
    ],
    "type": "exhibition"
  },
  {
    "id": 1270,
    "title": "Paris in the Twenties",
    "description": "Saturday, September 10, 2011 - Sunday, January 08, 2012",
    "objectIds": [
      1890
    ],
    "type": "exhibition"
  }
]
