[
  {
    "id": 1875,
    "title": "Seasonal Pleasures in Japanese Art, Part I",
    "description": null,
    "objectIds": [
      37190,
      40034,
      122080,
      122085,
      122086,
      122144,
      122150,
      122159,
      122160,
      122172,
      122179,
      122184,
      99427,
      122102,
      122115
    ],
    "type": "exhibition"
  },
  {
    "id": 1876,
    "title": "Seasonal Pleasures in Japanese Art, Part II",
    "description": null,
    "objectIds": [
      37190,
      40034,
      122086,
      122179,
      122184,
      122210,
      6612
    ],
    "type": "exhibition"
  },
  {
    "id": 286,
    "title": "Four Audacious Artists: Individualism in Japanese Art",
    "description": "Saturday, April 01, 1995 - Sunday, July 09, 1995",
    "objectIds": [
      37202,
      89718,
      37186,
      37191,
      37190,
      37184,
      37189,
      6358,
      37185,
      123100
    ],
    "type": "exhibition"
  }
]
