[
  {
    "id": 677,
    "title": "Hot & Cool: The Jazz Posters of Niklaus Troxler",
    "description": "Saturday, November 20, 2004 - Sunday, February 06, 2005",
    "objectIds": [
      94163,
      94164,
      94165,
      94166,
      94167,
      94168,
      94169,
      94170,
      94171,
      94172,
      94173,
      94174,
      94068,
      94175,
      94270,
      94276,
      94281,
      94284,
      94285,
      94286,
      94287,
      94288,
      94289,
      94292,
      94294,
      94296,
      95908,
      95909
    ],
    "type": "exhibition"
  }
]
